looki2000/looki2000.py
looki2000-0.1.dist-info/METADATA
looki2000-0.1.dist-info/WHEEL
looki2000-0.1.dist-info/top_level.txt
looki2000-0.1.dist-info/RECORD
