Metadata-Version: 2.1
Name: looki2000
Version: 0.1
Summary: My Python library
Author: lubek
Author-email: boryskostka369@gmail.com
Classifier: Programming Language :: Python :: 3
Classifier: License :: OSI Approved :: MIT License
Classifier: Operating System :: OS Independent
